bsdd.py
bsdd-0.8.3.dist-info/METADATA
bsdd-0.8.3.dist-info/WHEEL
bsdd-0.8.3.dist-info/top_level.txt
bsdd-0.8.3.dist-info/RECORD
