Metadata-Version: 2.4
Name: bsdd
Version: 0.8.3
Summary: Library to interact with the buildingSMART Data Dictionary
Author-email: Dion Moult <dion@thinkmoult.com>
Project-URL: Homepage, http://ifcopenshell.org
Project-URL: Documentation, https://docs.ifcopenshell.org
Project-URL: Issues, https://github.com/IfcOpenShell/IfcOpenShell/issues
Keywords: IFC,bSDD,BIM
Classifier: Development Status :: 4 - Beta
Classifier: Programming Language :: Python
Classifier: Programming Language :: Python :: 3.9
Classifier: Programming Language :: Python :: 3.10
Classifier: Programming Language :: Python :: 3.11
Classifier: Programming Language :: Python :: 3.12
Classifier: Programming Language :: Python :: Implementation :: CPython
Classifier: Programming Language :: Python :: Implementation :: PyPy
Classifier: License :: OSI Approved :: GNU Lesser General Public License v3 or later (LGPLv3+)
Requires-Python: >=3.9
Requires-Dist: requests
Requires-Dist: typing-extensions
Provides-Extra: dev
Requires-Dist: coverage[toml]>=6.5; extra == "dev"
Requires-Dist: pytest; extra == "dev"
